[
  {
    "homeABV": "BOS",
    "awayABV": "SJS",
    "homeGoalie": "BOS: Jeremy Swayman",
    "awayGoalie": "SJS: Alex Nedeljkovic",
    "homeScorers": {},
    "awayScorers": {},
    "allHomePoints": {
      "Sean Kuraly": 0.0363,
      "Hampus Lindholm": 0.0978,
      "Elias Lindholm": 0.2012,
      "Nikita Zadorov": 0.0224,
      "David Pastrnak": 0.9661,
      "Viktor Arvidsson": 0.3109,
      "Pavel Zacha": 0.2203,
      "Charlie McAvoy": 0.1651,
      "Riley Tufte": 0.0334,
      "Andrew Peeke": 0.0273,
      "Michael Eyssimont": 0.0881,
      "Tanner Jeannot": 0.0383,
      "Morgan Geekie": 0.5751,
      "Casey Mittelstadt": 0.1221,
      "Henri Jokiharju": 0.0107,
      "Mark Kastelic": 0.0541,
      "Michael Callahan": 0.0077,
      "Jordan Harris": 0.0249,
      "Jonathan Aspirot": 0.015,
      "Victor Soderstrom": 0,
      "Matěj  Blümel": 0.0219,
      "Marat Khusnutdinov": 0.0625,
      "Mason Lohrei": 0.0561,
      "Alex Steeves": 0.0944,
      "Fraser Minten": 0.1162,
      "Matthew Poitras": 0.0367,
      "Georgii Merkulov": 0
    },
    "allAwayPoints": {
      "Ryan Reaves": 0.005,
      "Nick Leddy": 0.0052,
      "Dmitry Orlov": 0.0247,
      "Tyler Toffoli": 0.3408,
      "John Klingberg": 0.1538,
      "Barclay Goodrow": 0.0223,
      "Alexander Wennberg": 0.1188,
      "Adam Gaudette": 0.1079,
      "Vincent Desharnais": 0.005,
      "Mario Ferraro": 0.0416,
      "Kiefer Sherwood": 0.3374,
      "Philipp Kurashev": 0.091,
      "Patrick Giles": 0.0085,
      "Shakir Mukhamadullin": 0.0469,
      "Ethan Cardwell": 0.0415,
      "Zack Ostapchuk": 0.0086,
      "Pavol Regenda": 0.3231,
      "Will Smith": 0.3493,
      "Macklin Celebrini": 0.9488,
      "Sam Dickinson": 0.0087,
      "Collin Graf": 0.1467,
      "Igor Chernyshov": 0.1574,
      "Michael Misa": 0.0882
    },
    "outcome": "BOS (OTW), BOS: 1.19164 v SJS: 1.18345      Expected difference: 0.00818999999999992, (BOS: 1.98607 v SJS: 1.97242) (BOS: 50.17% , SJS: 49.83%)",
    "startingTime": "19:05:00",
    "timeLastRun": "18:03:57",
    "homeMeanSquaredError": {},
    "awayMeanSquaredError": {},
    "homeLogLoss": {},
    "awayLogLoss": {},
    "correctLines": 0,
    "totalLines": 1
  },
  {
    "homeABV": "BUF",
    "awayABV": "WSH",
    "homeGoalie": {},
    "awayGoalie": "WSH: Charlie Lindgren",
    "homeScorers": {},
    "awayScorers": {},
    "allHomePoints": {
      "Luke Schenn": 0.0017,
      "Jason Zucker": 0.0953,
      "Sam Carrick": 0.0065,
      "Tanner Pearson": 0.013,
      "Mason Geertsen": 0,
      "Beck Malenstyn": 0.0059,
      "Logan Stanley": 0.0146,
      "Tage Thompson": 0.2702,
      "Conor Timmins": 0.003,
      "Josh Norris": 0.071,
      "Ryan McLeod": 0.0348,
      "Mattias Samuelsson": 0.0337,
      "Rasmus Dahlin": 0.1096,
      "Michael Kesselring": 0.0081,
      "Peyton Krebs": 0.0149,
      "Bowen Byram": 0.0289,
      "Ryan Johnson": 0,
      "Jack Quinn": 0.053,
      "Trevor Kuntar": 0,
      "Josh Dunne": 0.0021,
      "Josh Doan": 0.0679,
      "Owen Power": 0.0252,
      "Noah Ostlund": 0.0177,
      "Zach Benson": 0.0281,
      "Zach Metsa": 0.0025,
      "Konsta Helenius": 0.0171
    },
    "allAwayPoints": {
      "Alex Ovechkin": 0.7862,
      "Dylan McIlrath": 0,
      "Tom Wilson": 0.5232,
      "Trevor van Riemsdyk": 0.0094,
      "Sonny Milano": 0.0392,
      "Dylan Strome": 0.3004,
      "Anthony Beauvillier": 0.1664,
      "Matt Roy": 0.0188,
      "Jakob Chychrun": 0.6521,
      "Pierre-Luc Dubois": 0.2134,
      "Brandon Duhaime": 0.0268,
      "Timothy Liljegren": 0.0328,
      "Martin Fehérváry": 0.0356,
      "Rasmus Sandin": 0.0327,
      "Declan Chisholm": 0.0143,
      "Brett Leason": 0.0217,
      "Connor McMichael": 0.235,
      "Aliaksei Protas": 0.3901,
      "Justin Sourdif": 0.1315,
      "Hendrix Lapierre": 0.0088,
      "Bogdan Trineyev": 0,
      "Ivan Miroshnichenko": 0.0109,
      "Ethen Frank": 0.1164,
      "Ryan Leonard": 0.1694
    },
    "outcome": "WSH, BUF: 0.32368 v WSH: 1.37734      Expected difference: 1.05366, (BUF: 0.53947 v WSH: 2.29557) (BUF: 19.03% , WSH: 80.97%)",
    "startingTime": "19:05:00",
    "timeLastRun": "18:03:59",
    "homeMeanSquaredError": {},
    "awayMeanSquaredError": {},
    "homeLogLoss": {},
    "awayLogLoss": {},
    "correctLines": 0,
    "totalLines": 1
  },
  {
    "homeABV": "TOR",
    "awayABV": "ANA",
    "homeGoalie": "TOR: Joseph Woll",
    "awayGoalie": {},
    "homeScorers": {},
    "awayScorers": {},
    "allHomePoints": {
      "John Tavares": 0.3593,
      "Oliver Ekman-Larsson": 0.0622,
      "Calle Jarnkrok": 0.0209,
      "Morgan Rielly": 0.0942,
      "Jake McCabe": 0.0171,
      "Matt Benning": 0,
      "Max Domi": 0.0578,
      "Dakota Mermis": 0.0128,
      "William Nylander": 0.4896,
      "Dakota Joshua": 0.0325,
      "Brandon Carlo": 0.0023,
      "Steven Lorentz": 0.0163,
      "Philippe Myers": 0.0063,
      "Auston Matthews": 0.7082,
      "Troy Stecher": 0.0179,
      "Bo Groulx": 0,
      "Simon Benoit": 0.0021,
      "Henry Thrun": 0.008,
      "Nicholas Robertson": 0.0877,
      "Matias Maccelli": 0.0867,
      "Matthew Knies": 0.2211,
      "Marshall Rifai": 0,
      "Easton Cowan": 0.0667,
      "Jacob Quillan": 0
    },
    "allAwayPoints": {
      "Alex Killorn": 0.1099,
      "Chris Kreider": 0.2531,
      "Radko Gudas": 0.0123,
      "Mikael Granlund": 0.2369,
      "Jacob Trouba": 0.0971,
      "Ross Johnston": 0.004,
      "Frank Vatrano": 0.1163,
      "Jansen Harkins": 0.011,
      "Jeffrey Viel": 0.0207,
      "Ryan Poehling": 0.0549,
      "Drew Helleson": 0.0152,
      "Jackson LaCombe": 0.1452,
      "Nikita Nesterenko": 0.0193,
      "Sam Colangelo": 0.0594,
      "Mason McTavish": 0.1821,
      "Olen Zellweger": 0.0793,
      "Cutter Gauthier": 0.4867,
      "Pavel Mintyukov": 0.0407,
      "Leo Carlsson": 0.2963,
      "Beckett Sennecke": 0.2783,
      "Tim Washe": 0.0201
    },
    "outcome": "ANA, TOR: 0.82935 v ANA: 0.8886      Expected difference: 0.0592499999999998, (TOR: 1.38225 v ANA: 1.481) (TOR: 48.28% , ANA: 51.72%)",
    "startingTime": "19:05:00",
    "timeLastRun": "18:04:01",
    "homeMeanSquaredError": {},
    "awayMeanSquaredError": {},
    "homeLogLoss": {},
    "awayLogLoss": {},
    "correctLines": 0,
    "totalLines": 1
  },
  {
    "homeABV": "TBL",
    "awayABV": "DET",
    "homeGoalie": {},
    "awayGoalie": "DET: John Gibson",
    "homeScorers": ["Nikita Kucherov, TBL: 0.43672      (0.727866666666667)", "Brandon Hagel, TBL: 0.35562      (0.5927)"],
    "awayScorers": "Alex DeBrincat, DET: 0.36325      (0.605416666666667)",
    "allHomePoints": {
      "Corey Perry": 0.2119,
      "Ryan McDonagh": 0.0677,
      "Victor Hedman": 0.1724,
      "Nikita Kucherov": 1.2478,
      "Yanni Gourde": 0.0972,
      "Zemgus Girgensons": 0.0587,
      "Scott Sabourin": 0.0084,
      "Jake Guentzel": 0.944,
      "Oliver Bjorkstrand": 0.2033,
      "Steven Santini": 0,
      "Brayden Point": 0.6806,
      "Anthony Cirelli": 0.3601,
      "Brandon Hagel": 1.0161,
      "Charle-Edouard D'Astous": 0.0465,
      "Pontus Holmberg": 0.0776,
      "Simon Lundmark": 0,
      "Jakob Pelletier": 0.048,
      "Max Crozier": 0.022,
      "Mitchell Chaffee": 0.0585,
      "Maxim Groshev": 0,
      "Gage Goncalves": 0.0633,
      "J.J. Moser": 0.0948,
      "Declan Carlile": 0.0156,
      "Conor Geekie": 0.0387
    },
    "allAwayPoints": {
      "James van Riemsdyk": 0.155,
      "Patrick Kane": 0.3557,
      "Travis Hamonic": 0.0045,
      "Ben Chiarot": 0.0651,
      "Justin Faulk": 0.2016,
      "Erik Gustafsson": 0.0224,
      "J.T. Compher": 0.0849,
      "Mason Appleton": 0.0591,
      "Alex DeBrincat": 1.0379,
      "Dominik Shine": 0.0172,
      "Michael Rasmussen": 0.0596,
      "Jacob Bernard-Docker": 0.0051,
      "John Leonard": 0.094,
      "Moritz Seider": 0.2139,
      "Albert Johansson": 0.0156,
      "Lucas Raymond": 0.4733,
      "Simon Edvinsson": 0.1136,
      "Marco Kasper": 0.1351,
      "Nate Danielson": 0.0308,
      "Axel Sandin-Pellikka": 0.0538,
      "Emmitt Finnie": 0.1417,
      "Michael Brandsegg-Nygård": 0
    },
    "outcome": "TBL, TBL: 1.93659 v DET: 1.16902      Expected difference: 0.76757, (TBL: 3.22765 v DET: 1.94837) (TBL: 62.36% , DET: 37.64%)",
    "startingTime": "19:05:00",
    "timeLastRun": "18:04:02",
    "homeMeanSquaredError": {},
    "awayMeanSquaredError": {},
    "homeLogLoss": {},
    "awayLogLoss": {},
    "correctLines": 0,
    "totalLines": 4
  },
  {
    "homeABV": "FLA",
    "awayABV": "CBJ",
    "homeGoalie": "FLA: Sergei Bobrovsky",
    "awayGoalie": "CBJ: Elvis Merzlikins",
    "homeScorers": {},
    "awayScorers": {},
    "allHomePoints": {
      "Dmitry Kulikov": 0.0108,
      "Vinnie Hinostroza": 0.0145,
      "Tomas Nosek": 0.0014,
      "Aaron Ekblad": 0.0295,
      "Sam Reinhart": 0.3519,
      "Sam Bennett": 0.2604,
      "Gustav Forsling": 0.0339,
      "A.J. Greer": 0.0236,
      "Evan Rodrigues": 0.0822,
      "Niko Mikkola": 0.0202,
      "Matthew Tkachuk": 0.2943,
      "Luke Kunin": 0.0128,
      "Noah Gregor": 0.007,
      "Jesper Boqvist": 0.0132,
      "Jack Studnicka": 0,
      "Eetu Luostarinen": 0.0376,
      "Cole Reinhardt": 0.0064,
      "Tobias Bjornfot": 0.0148,
      "Donovan Sebrango": 0,
      "Mackie Samoskevich": 0.0493,
      "Jack Devine": 0,
      "Sandis Vilmanis": 0.0174,
      "Mikulas Hovorka": 0
    },
    "allAwayPoints": {
      "Brendan Smith": 0.0028,
      "Charlie Coyle": 0.1429,
      "Erik Gudbranson": 0.0117,
      "Boone Jenner": 0.1516,
      "Brendan Gaunce": 0.0176,
      "Damon Severson": 0.0444,
      "Miles Wood": 0.0578,
      "Sean Monahan": 0.1809,
      "Danton Heinen": 0.0277,
      "Dysin Mayo": 0,
      "Zach Werenski": 0.651,
      "Ivan Provorov": 0.0975,
      "Conor Garland": 0.1823,
      "Mason Marchment": 0.1892,
      "Dante Fabbro": 0.043,
      "Mathieu Olivier": 0.0977,
      "Zachary Aston-Reese": 0.0137,
      "Isac Lundeström": 0.0125,
      "Kirill Marchenko": 0.4568,
      "Jake Christiansen": 0.0012,
      "Egor Zamula": 0.0042,
      "Dmitri Voronkov": 0.1751,
      "Mikael Pyyhtia": 0.0193,
      "Kent Johnson": 0.0938,
      "Cole Sillinger": 0.0692,
      "Luca Del Bel Belluz": 0.0092,
      "Denton Mateychuk": 0.0696,
      "Adam Fantilli": 0.3096,
      "Luca Pinelli": 0
    },
    "outcome": "CBJ, FLA: 0.44843 v CBJ: 1.09628      Expected difference: 0.64785, (FLA: 0.74738 v CBJ: 1.82713) (FLA: 29.03% , CBJ: 70.97%)",
    "startingTime": "19:05:00",
    "timeLastRun": "18:04:04",
    "homeMeanSquaredError": {},
    "awayMeanSquaredError": {},
    "homeLogLoss": {},
    "awayLogLoss": {},
    "correctLines": 0,
    "totalLines": 1
  },
  {
    "homeABV": "NJD",
    "awayABV": "CGY",
    "homeGoalie": "NJD: Jacob Markstrom",
    "awayGoalie": "CGY: Dustin Wolf",
    "homeScorers": {},
    "awayScorers": {},
    "allHomePoints": {
      "Evgenii Dadonov": 0.0574,
      "Brenden Dillon": 0.0116,
      "Nick Bjugstad": 0.062,
      "Dougie Hamilton": 0.2227,
      "Connor Brown": 0.1112,
      "Jonas Siegenthaler": 0.0039,
      "Timo Meier": 0.4798,
      "Colton White": 0,
      "Dennis Cholowski": 0.0105,
      "Jesper Bratt": 0.2574,
      "Cody Glass": 0.111,
      "Nico Hischier": 0.5237,
      "Johnathan Kovacevic": 0.0036,
      "Paul Cotter": 0.0371,
      "Angus Crookshank": 0.0137,
      "Jack Hughes": 0.7273,
      "Nathan Légaré": 0,
      "Arseny Gritsyuk": 0.1543,
      "Dawson Mercer": 0.1995,
      "Luke Hughes": 0.1099,
      "Shane Lachance": 0,
      "Seamus Casey": 0.0917,
      "Simon Nemec": 0.1098,
      "Brian Halonen": 0.012,
      "Xavier Parent": 0,
      "Lenni Hameenaho": 0.0526,
      "Maxim Tsyplakov": 0.0243
    },
    "allAwayPoints": {
      "Mikael Backlund": 0.1908,
      "Blake Coleman": 0.2251,
      "Ryan Strome": 0.0496,
      "Olli Määttä": 0.0038,
      "Joel Hanley": 0.0023,
      "Justin Kirkland": 0.0072,
      "Victor Olofsson": 0.1143,
      "Dryden Hunt": 0,
      "Ryan Lomberg": 0.0105,
      "Jake Bean": 0.016,
      "Morgan Frost": 0.1194,
      "Joel Farabee": 0.1296,
      "Kevin Bahl": 0.021,
      "Martin Pospisil": 0.0201,
      "Yegor Sharangovich": 0.1485,
      "Brayden Pachal": 0.0048,
      "John Beecher": 0.0061,
      "Connor Zary": 0.1032,
      "Yan Kuznetsov": 0.0391,
      "Rory Kerins": 0,
      "Daniil Miromanov": 0.0193,
      "Matt Coronato": 0.2361,
      "William Stromgren": 0,
      "Adam Klapka": 0.025,
      "Hunter Brzustewicz": 0.018,
      "Samuel Honzek": 0.0375,
      "Zayne Parekh": 0.0067,
      "Sam Morton": 0.0287,
      "Matvei Gridin": 0.1207
    },
    "outcome": "NJD, NJD: 1.18542 v CGY: 0.59617      Expected difference: 0.58925, (NJD: 1.9757 v CGY: 0.99362) (NJD: 66.54% , CGY: 33.46%)",
    "startingTime": "19:05:00",
    "timeLastRun": "18:04:06",
    "homeMeanSquaredError": {},
    "awayMeanSquaredError": {},
    "homeLogLoss": {},
    "awayLogLoss": {},
    "correctLines": 0,
    "totalLines": 1
  },
  {
    "homeABV": "CAR",
    "awayABV": "STL",
    "homeGoalie": {},
    "awayGoalie": "STL: Jordan Binnington",
    "homeScorers": {},
    "awayScorers": {},
    "allHomePoints": {
      "Jordan Staal": 0.0542,
      "Nicolas Deslauriers": 0.0013,
      "Taylor Hall": 0.0625,
      "Mike Reilly": 0.0069,
      "Mark Jankowski": 0.0179,
      "Jordan Martinook": 0.034,
      "Jaccob Slavin": 0.0187,
      "William Carrier": 0.0146,
      "Nikolaj Ehlers": 0.156,
      "Sebastian Aho": 0.1986,
      "Jalen Chatfield": 0.014,
      "Sean Walker": 0.0369,
      "Eric Robinson": 0.0336,
      "Jesperi Kotkaniemi": 0.0153,
      "Andrei Svechnikov": 0.1674,
      "Noah Philp": 0.0083,
      "Domenick Fensore": 0,
      "Seth Jarvis": 0.3027,
      "Alexander Nikishin": 0.0417,
      "Logan Stankoven": 0.0661,
      "Justin Robidas": 0.0207,
      "Jackson Blake": 0.0909,
      "Joel Nystrom": 0.0053,
      "Bradly Nadeau": 0.0379,
      "Charles Alexis Legault": 0.0229
    },
    "allAwayPoints": {
      "Justin Holl": 0.0063,
      "Cam Fowler": 0.0389,
      "Colton Parayko": 0.0869,
      "Oskar Sundqvist": 0.0269,
      "Pavel Buchnevich": 0.2318,
      "Nathan Walker": 0.0381,
      "Jordan Kyrou": 0.4307,
      "Robert Thomas": 0.2925,
      "Alexey Toropchenko": 0.023,
      "Pius Suter": 0.1846,
      "Tyler Tucker": 0.0252,
      "Jonatan Berggren": 0.0762,
      "Hugh McGing": 0.1358,
      "Philip Broberg": 0.0698,
      "Hunter Skinner": 0,
      "Dylan Holloway": 0.385,
      "Jake Neighbours": 0.1598,
      "Jack Finley": 0.0106,
      "Matthew Kessel": 0.0107,
      "Logan Mailloux": 0.0353,
      "Aleksanteri Kaskimaki": 0,
      "Jimmy Snuggerud": 0.2426,
      "Dalibor Dvorsky": 0.0771,
      "Theo Lindstein": 0,
      "Otto Stenberg": 0.0185
    },
    "outcome": "STL, CAR: 0.50001 v STL: 0.9122      Expected difference: 0.41219, (CAR: 0.83335 v STL: 1.52033) (CAR: 35.41% , STL: 64.59%)",
    "startingTime": "19:05:00",
    "timeLastRun": "18:04:07",
    "homeMeanSquaredError": {},
    "awayMeanSquaredError": {},
    "homeLogLoss": {},
    "awayLogLoss": {},
    "correctLines": 0,
    "totalLines": 1
  },
  {
    "homeABV": "DAL",
    "awayABV": "EDM",
    "homeGoalie": "DAL: Jake Oettinger",
    "awayGoalie": "EDM: Tristan Jarry",
    "homeScorers": {},
    "awayScorers": ["Leon Draisaitl, EDM: 0.42989      (0.716483333333333)", "Connor McDavid, EDM: 0.42021      (0.70035)"],
    "allHomePoints": {
      "Jamie Benn": 0.0996,
      "Tyler Myers": 0.022,
      "Matt Duchene": 0.1848,
      "Alexander Petrovic": 0.0135,
      "Colin Blackwell": 0.0171,
      "Esa Lindell": 0.0396,
      "Adam Erne": 0.0275,
      "Michael Bunting": 0.1341,
      "Kyle Capobianco": 0.009,
      "Sam Steel": 0.0471,
      "Nathan Bastian": 0.0215,
      "Jason Robertson": 0.6405,
      "Miro Heiskanen": 0.1546,
      "Oskar Bäck": 0.0107,
      "Nils Lundkvist": 0.0206,
      "Ilya Lyubushkin": 0.0041,
      "Thomas Harley": 0.1363,
      "Vladislav Kolyachonok": 0.0135,
      "Mavrik Bourque": 0.0906,
      "Wyatt Johnston": 0.5068,
      "Lian Bichsel": 0.0172,
      "Justin Hryckowian": 0.036,
      "Arttu Hyry": 0
    },
    "allAwayPoints": {
      "Adam Henrique": 0.0574,
      "Mattias Ekholm": 0.1292,
      "Zach Hyman": 0.8423,
      "Ryan Nugent-Hopkins": 0.3281,
      "Connor Murphy": 0.0293,
      "Jason Dickinson": 0.0609,
      "Darnell Nurse": 0.1392,
      "Leon Draisaitl": 1.2283,
      "Kasperi Kapanen": 0.0942,
      "Jake Walman": 0.2296,
      "Connor McDavid": 1.2006,
      "Jack Roslovic": 0.2705,
      "Trent Frederic": 0.0334,
      "Riley Stillman": 0,
      "Evan Bouchard": 0.5262,
      "Alec Regula": 0,
      "Spencer Stastney": 0.0119,
      "Vasily Podkolzin": 0.1164,
      "Isaac Howard": 0.0269,
      "Matt Savoie": 0.0865,
      "Josh Samanski": 0,
      "Connor Clattenburg": 0.0268,
      "Quinn Hutson": 0.0433
    },
    "outcome": "EDM, DAL: 0.78638 v EDM: 1.9183      Expected difference: 1.13192, (DAL: 1.31063 v EDM: 3.19717) (DAL: 29.07% , EDM: 70.93%)",
    "startingTime": "20:05:00",
    "timeLastRun": "18:04:08",
    "homeMeanSquaredError": {},
    "awayMeanSquaredError": {},
    "homeLogLoss": {},
    "awayLogLoss": {},
    "correctLines": 0,
    "totalLines": 3
  },
  {
    "homeABV": "MIN",
    "awayABV": "PHI",
    "homeGoalie": "MIN: Jesper Wallstedt",
    "awayGoalie": {},
    "homeScorers": ["Kirill Kaprizov, MIN: 0.50116      (0.835266666666667)", "Matt Boldy, MIN: 0.37742      (0.629033333333333)"],
    "awayScorers": {},
    "allHomePoints": {
      "Jeff Petry": 0.0021,
      "Zach Bogosian": 0.0222,
      "Jared Spurgeon": 0.0795,
      "Marcus Johansson": 0.1402,
      "Mats Zuccarello": 0.3198,
      "Tyler Pitlick": 0.0123,
      "Vladimir Tarasenko": 0.1908,
      "Jonas Brodin": 0.0539,
      "Michael McCarron": 0.0508,
      "Ryan Hartman": 0.2394,
      "Robby Fabbri": 0.0719,
      "Nicolas Aube-Kubel": 0.0098,
      "Jake Middleton": 0.0299,
      "Joel Eriksson Ek": 0.4795,
      "Yakov Trenin": 0.0403,
      "Kirill Kaprizov": 1.4319,
      "Quinn Hughes": 0.3323,
      "Nico Sturm": 0.029,
      "Matt Boldy": 1.0783,
      "Daemon Hunt": 0,
      "Brock Faber": 0.2709,
      "Matt Kiersted": 0,
      "Carson Lambos": 0,
      "Hunter Haight": 0,
      "Danila Yurov": 0.0726,
      "David Spacek": 0
    },
    "allAwayPoints": {
      "Nick Seeler": 0.0197,
      "Sean Couturier": 0.1072,
      "Luke Glendening": 0.0039,
      "Rasmus Ristolainen": 0.0438,
      "Garnet Hathaway": 0.0129,
      "Travis Sanheim": 0.0807,
      "Christian Dvorak": 0.1453,
      "Travis Konecny": 0.4195,
      "Noah Juulsen": 0.0037,
      "Lane Pederson": 0,
      "Carl Grundstrom": 0.065,
      "Owen Tippett": 0.3379,
      "Noah Cates": 0.1234,
      "Adam Ginning": 0,
      "Trevor Zegras": 0.3,
      "Cam York": 0.0477,
      "Jacob Gaucher": 0,
      "Emil Andrae": 0.0077,
      "Jamie Drysdale": 0.073,
      "Tyson Foerster": 0.3119,
      "Alex Bump": 0.2909,
      "Nikita Grebenkin": 0.0123,
      "Denver Barkey": 0.0393,
      "Matvei Michkov": 0.2457,
      "Jett Luchanko": 0
    },
    "outcome": "MIN, MIN: 1.73507 v PHI: 0.94198      Expected difference: 0.79309, (MIN: 2.89178 v PHI: 1.56997) (MIN: 64.81% , PHI: 35.19%)",
    "startingTime": "20:05:00",
    "timeLastRun": "18:04:10",
    "homeMeanSquaredError": {},
    "awayMeanSquaredError": {},
    "homeLogLoss": {},
    "awayLogLoss": {},
    "correctLines": 0,
    "totalLines": 3
  },
  {
    "homeABV": "WPG",
    "awayABV": "NYR",
    "homeGoalie": "WPG: Connor Hellebuyck",
    "awayGoalie": "NYR: Igor Shesterkin",
    "homeScorers": "Kyle Connor, WPG: 0.39662      (0.661033333333333)",
    "awayScorers": {},
    "allHomePoints": {
      "Jonathan Toews": 0.0793,
      "Gustav Nyquist": 0.0479,
      "Dylan DeMelo": 0.0339,
      "Adam Lowry": 0.0931,
      "Mark Scheifele": 0.7718,
      "Josh Morrissey": 0.2973,
      "Haydn Fleury": 0,
      "Kyle Connor": 1.1332,
      "Gabriel Vilardi": 0.4643,
      "Dylan Samberg": 0.0487,
      "Alex Iafallo": 0.1136,
      "Jacob Bryson": 0.0053,
      "Morgan Barron": 0.0891,
      "Cole Koepke": 0.0507,
      "Ville Heinola": 0,
      "Cole Perfetti": 0.1984,
      "Isaak Phillips": 0.0364,
      "Walker Duehr": 0.0135,
      "Isak Rosen": 0.058,
      "Nikita Chibrikov": 0.0241,
      "Brad Lambert": 0.0183,
      "Elias Salomonsson": 0.0412,
      "Danil Zhilkin": 0,
      "Parker Ford": 0.0073
    },
    "allAwayPoints": {
      "Justin Dowling": 0.0047,
      "Vincent Trocheck": 0.3229,
      "Mika Zibanejad": 0.5113,
      "Anton Blidh": 0,
      "Jonny Brodzinski": 0.0518,
      "Conor Sheary": 0.0216,
      "Will Borgen": 0.0379,
      "Vladislav Gavrikov": 0.1285,
      "Adam Fox": 0.1397,
      "Urho Vaakanainen": 0.0052,
      "Matthew Robertson": 0.0371,
      "Juuso Parssinen": 0.0219,
      "Adam Edstrom": 0.0182,
      "Tye Kartye": 0.0213,
      "Braden Schneider": 0.0313,
      "Alexis Lafrenière": 0.2292,
      "Brett Berard": 0.0334,
      "Brendan Brisson": 0,
      "Will Cuylle": 0.2132,
      "Scott Morrow": 0.0046,
      "Vincent Iorio": 0,
      "Jaroslav Chmelar": 0.0133,
      "Noah Laba": 0.0394,
      "Gabe Perreault": 0.1094
    },
    "outcome": "WPG, WPG: 1.26899 v NYR: 0.69849      Expected difference: 0.5705, (WPG: 2.11498 v NYR: 1.16415) (WPG: 64.5% , NYR: 35.5%)",
    "startingTime": "20:05:00",
    "timeLastRun": "18:04:11",
    "homeMeanSquaredError": {},
    "awayMeanSquaredError": {},
    "homeLogLoss": {},
    "awayLogLoss": {},
    "correctLines": 0,
    "totalLines": 2
  },
  {
    "homeABV": "UTA",
    "awayABV": "CHI",
    "homeGoalie": "UTA: Karel Vejmelka",
    "awayGoalie": "CHI: Arvid Soderblom",
    "homeScorers": {},
    "awayScorers": {},
    "allHomePoints": {
      "Ian Cole": 0.0033,
      "Andrew Agozzino": 0,
      "Alexander Kerfoot": 0.0171,
      "Liam O'Brien": 0.0036,
      "Nate Schmidt": 0.0122,
      "MacKenzie Weegar": 0.0309,
      "Nick Schmaltz": 0.1382,
      "Lawson Crouse": 0.0527,
      "John Marino": 0.0083,
      "Kevin Stenlund": 0.0136,
      "Kevin Rooney": 0.0073,
      "Clayton Keller": 0.1551,
      "Michael Carcone": 0.038,
      "Kailer Yamamoto": 0.0219,
      "Nick DeSimone": 0.0069,
      "Sean Durzi": 0.0339,
      "Barrett Hayton": 0.0507,
      "Jack McBain": 0.0203,
      "JJ Peterka": 0.1106,
      "Dylan Guenther": 0.2243,
      "Logan Cooley": 0.1379,
      "Maveric Lamoureux": 0.0053,
      "Dmitri Simashev": 0,
      "Daniil But": 0.0197
    },
    "allAwayPoints": {
      "Teuvo Teravainen": 0.1505,
      "Matt Grzelcyk": 0.0025,
      "Dominic Toninato": 0,
      "Andre Burakovsky": 0.1109,
      "Tyler Bertuzzi": 0.3998,
      "Ryan Donato": 0.2274,
      "Sam Lafferty": 0.0101,
      "Andrew Mangiapane": 0.0629,
      "Alex Vlasic": 0.0278,
      "Ilya Mikheyev": 0.1897,
      "Louis Crevier": 0.0497,
      "Landon Slaggert": 0.0264,
      "Wyatt Kaiser": 0.0483,
      "Ethan Del Mastro": 0.0239,
      "Ryan Greene": 0.0796,
      "Kevin Korchinski": 0.0135,
      "Frank Nazar": 0.218,
      "Sam Rinzel": 0.0786,
      "Connor Bedard": 0.7836,
      "Nick Lardis": 0.1149,
      "Artyom Levshunov": 0.0216
    },
    "outcome": "CHI, UTA: 0.38917 v CHI: 0.92392      Expected difference: 0.53475, (UTA: 0.64862 v CHI: 1.53987) (UTA: 29.64% , CHI: 70.36%)",
    "startingTime": "21:05:00",
    "timeLastRun": "18:04:12",
    "homeMeanSquaredError": {},
    "awayMeanSquaredError": {},
    "homeLogLoss": {},
    "awayLogLoss": {},
    "correctLines": 0,
    "totalLines": 1
  },
  {
    "homeABV": "VAN",
    "awayABV": "NSH",
    "homeGoalie": "VAN: Nikita Tolopilo",
    "awayGoalie": {},
    "homeScorers": {},
    "awayScorers": {},
    "allHomePoints": {
      "Evander Kane": 0.1659,
      "Joseph LaBate": 0,
      "Mackenzie MacEachern": 0.0207,
      "Teddy Blueger": 0.0821,
      "Marcus Pettersson": 0.0115,
      "Brock Boeser": 0.2461,
      "Jake DeBrusk": 0.237,
      "Filip Hronek": 0.0687,
      "Elias Pettersson": 0.0075,
      "Curtis Douglas": 0,
      "Linus Karlsson": 0.0671,
      "Nils Hoglander": 0.0215,
      "Marco Rossi": 0.1449,
      "Nils Aman": 0.0037,
      "Aatu Räty": 0.0238,
      "Arshdeep Bains": 0.0057,
      "Jonathan Lekkerimäki": 0.0359,
      "Liam Ohgren": 0.0382,
      "Victor Mancini": 0.0061,
      "Max Sasson": 0.0455,
      "Tom Willander": 0.0225,
      "Zeev Buium": 0.0302,
      "Braeden Cootes": 0
    },
    "allAwayPoints": {
      "Steven Stamkos": 0.3762,
      "Roman Josi": 0.2899,
      "Ryan O'Reilly": 0.2629,
      "Erik Haula": 0.0829,
      "Jonathan Marchessault": 0.2225,
      "Brady Skjei": 0.0401,
      "Filip Forsberg": 0.541,
      "Andreas Englund": 0.0027,
      "Tyson Jost": 0.0229,
      "Nicolas Hague": 0.0232,
      "Nick Perbix": 0.0219,
      "Ozzy Wiesblatt": 0.0047,
      "Justin Barron": 0.0106,
      "Luke Evangelista": 0.1017,
      "Ryan Ufko": 0.0517,
      "Zachary L'Heureux": 0.0271,
      "Fedor Svechkov": 0.0217,
      "Joakim Kemell": 0,
      "Reid Schaefer": 0.0337,
      "Matthew Wood": 0.0906,
      "Brady Martin": 0
    },
    "outcome": "NSH, VAN: 0.50792 v NSH: 0.77975      Expected difference: 0.27183, (VAN: 0.84653 v NSH: 1.29958) (VAN: 39.44% , NSH: 60.56%)",
    "startingTime": "22:05:00",
    "timeLastRun": "18:04:15",
    "homeMeanSquaredError": {},
    "awayMeanSquaredError": {},
    "homeLogLoss": {},
    "awayLogLoss": {},
    "correctLines": 0,
    "totalLines": 1
  },
  {
    "homeABV": "VGK",
    "awayABV": "PIT",
    "homeGoalie": "VGK: Adin Hill",
    "awayGoalie": "PIT: Arturs Silovs",
    "homeScorers": {},
    "awayScorers": {},
    "allHomePoints": {
      "Brayden McNabb": 0.0292,
      "Reilly Smith": 0.0927,
      "Nic Dowd": 0.0393,
      "Mark Stone": 0.4398,
      "Brandon Saad": 0.0683,
      "William Karlsson": 0.198,
      "Tomas Hertl": 0.4392,
      "Colton Sissons": 0.0338,
      "Ben Hutton": 0.0514,
      "Jaycob Megna": 0,
      "Shea Theodore": 0.1497,
      "Ivan Barbashev": 0.2001,
      "Noah Hanifin": 0.0977,
      "Rasmus Andersson": 0.2155,
      "Jack Eichel": 0.7163,
      "Keegan Kolesar": 0.0289,
      "Jeremy Lauzon": 0,
      "Mitch Marner": 0.3083,
      "Brett Howden": 0.1343,
      "Tanner Laczynski": 0.0083,
      "Dylan Coghlan": 0,
      "Jonas Rondbjerg": 0,
      "Kaedan Korczak": 0.0132,
      "Raphael Lavoie": 0,
      "Pavel Dorofeyev": 0.5877,
      "Cole Smith": 0.0403,
      "Alexander Holtz": 0.0335,
      "Braeden Bowman": 0.0866,
      "Kai Uchacz": 0
    },
    "allAwayPoints": {
      "Kris Letang": 0.0601,
      "Erik Karlsson": 0.1169,
      "Bryan Rust": 0.4216,
      "Rickard Rakell": 0.3367,
      "Mathew Dumba": 0.009,
      "Connor Clifton": 0.0091,
      "Ryan Graves": 0.0074,
      "Anthony Mantha": 0.1868,
      "Bokondji Imama": 0.0047,
      "Tommy Novak": 0.0955,
      "Parker Wotherspoon": 0.0131,
      "Noel Acciari": 0.0336,
      "Ryan Shea": 0.0187,
      "Joona Koppanen": 0.005,
      "Connor Dewar": 0.0679,
      "Blake Lizotte": 0.0349,
      "Elmer Soderblom": 0.0198,
      "Ilya Solovyov": 0.0083,
      "Egor Chinakhov": 0.1213,
      "Tristan Broz": 0,
      "Ville Koivunen": 0.0175,
      "Rutger McGroarty": 0.0418,
      "Owen Pickering": 0.0037,
      "Harrison Brunicke": 0.0299,
      "Ben Kindel": 0.1513
    },
    "outcome": "VGK, VGK: 1.40424 v PIT: 0.63509      Expected difference: 0.76915, (VGK: 2.3404 v PIT: 1.05848) (VGK: 68.86% , PIT: 31.14%)",
    "startingTime": "22:05:00",
    "timeLastRun": "18:04:16",
    "homeMeanSquaredError": {},
    "awayMeanSquaredError": {},
    "homeLogLoss": {},
    "awayLogLoss": {},
    "correctLines": 0,
    "totalLines": 1
  },
  {
    "homeABV": "SEA",
    "awayABV": "COL",
    "homeGoalie": "SEA: Joey Daccord",
    "awayGoalie": "COL: Scott Wedgewood",
    "homeScorers": {},
    "awayScorers": "Nathan MacKinnon, COL: 0.52914      (0.8819)",
    "allHomePoints": {
      "Jordan Eberle": 0.467,
      "Adam Larsson": 0.0793,
      "Jamie Oleksiak": 0.0286,
      "Chandler Stephenson": 0.1786,
      "John Hayden": 0.0124,
      "Frederick Gaudreau": 0.093,
      "Jared McCann": 0.5403,
      "Brandon Montour": 0.4555,
      "Vince Dunn": 0.2975,
      "Ryan Lindgren": 0.0214,
      "Joshua Mahura": 0.0092,
      "Cale Fleury": 0.0279,
      "Eeli Tolvanen": 0.2398,
      "Kaapo Kakko": 0.1499,
      "Matty Beniers": 0.3574,
      "Ryan Winterton": 0.0237,
      "Ryker Evans": 0.0534,
      "Jacob Melanson": 0.0231,
      "Jani Nyman": 0.1121,
      "Shane Wright": 0.1416,
      "Ben Meyers": 0.073,
      "Oscar Fisker Molgaard": 0,
      "Berkly Catton": 0.0585
    },
    "allAwayPoints": {
      "Brent Burns": 0.1187,
      "Nazem Kadri": 0.4166,
      "Brock Nelson": 0.4881,
      "Josh Manson": 0.0507,
      "T.J. Tynan": 0,
      "Brett Kulak": 0.0257,
      "Nathan MacKinnon": 1.5118,
      "Valeri Nichushkin": 0.3579,
      "Devon Toews": 0.0809,
      "Nicolas Roy": 0.0595,
      "Keaton Middleton": 0,
      "Alex Barré-Boulet": 0,
      "Martin Necas": 0.5742,
      "Cale Makar": 0.5845,
      "Parker Kelly": 0.0736,
      "Jack Drury": 0.0522,
      "Joel Kiviranta": 0.0355,
      "Jack Ahcan": 0,
      "Zakhar Bardakov": 0.0021,
      "Taylor Makar": 0,
      "Tristen Nielsen": 0,
      "Nick Blankenburg": 0.0617,
      "Ivan Ivan": 0.0147,
      "Gavin Brindley": 0.034,
      "Jason Polin": 0,
      "Sam Malinski": 0.0396
    },
    "outcome": "COL, SEA: 1.20508 v COL: 1.60365      Expected difference: 0.39857, (SEA: 2.00847 v COL: 2.67275) (SEA: 42.9% , COL: 57.1%)",
    "startingTime": "22:05:00",
    "timeLastRun": "18:04:21",
    "homeMeanSquaredError": {},
    "awayMeanSquaredError": {},
    "homeLogLoss": {},
    "awayLogLoss": {},
    "correctLines": 0,
    "totalLines": 2
  }
]
