[
  {
    "homeABV": "STL",
    "awayABV": "VGK",
    "homeGoalie": "STL: Joel Hofer",
    "awayGoalie": {},
    "homeScorers": {},
    "awayScorers": {},
    "outcome": "VGK, STL: 0.70893 v VGK: 0.91367      Expected difference: 0.20474, (STL: 1.18155 v VGK: 1.52278) (STL: 43.69% , VGK: 56.31%)",
    "startingTime": "15:05:00",
    "timeLastRun": "14:02:23",
    "correctLines": 0,
    "totalLines": 1
  },
  {
    "homeABV": "FLA",
    "awayABV": "NYR",
    "homeGoalie": {},
    "awayGoalie": {},
    "homeScorers": {},
    "awayScorers": {},
    "outcome": "FLA, FLA: 1.17356 v NYR: 0.48316      Expected difference: 0.6904, (FLA: 1.95593 v NYR: 0.80527) (FLA: 70.84% , NYR: 29.16%)",
    "startingTime": "20:05:00",
    "timeLastRun": "14:02:25",
    "correctLines": 0,
    "totalLines": 1
  },
  {
    "homeABV": "VAN",
    "awayABV": "SEA",
    "homeGoalie": "VAN: Thatcher Demko",
    "awayGoalie": {},
    "homeScorers": {},
    "awayScorers": {},
    "outcome": "VAN, VAN: 0.82999 v SEA: 0.6229      Expected difference: 0.20709, (VAN: 1.38332 v SEA: 1.03817) (VAN: 57.13% , SEA: 42.87%)",
    "startingTime": "22:35:00",
    "timeLastRun": "14:02:26",
    "correctLines": 0,
    "totalLines": 1
  },
  {
    "homeABV": "ANA",
    "awayABV": "MIN",
    "homeGoalie": "ANA: Lukas Dostal",
    "awayGoalie": {},
    "homeScorers": {},
    "awayScorers": {},
    "outcome": "ANA, ANA: 1.17369 v MIN: 0.51017      Expected difference: 0.66352, (ANA: 1.95615 v MIN: 0.85028) (ANA: 69.7% , MIN: 30.3%)",
    "startingTime": "22:35:00",
    "timeLastRun": "14:02:27",
    "correctLines": 0,
    "totalLines": 1
  }
]
